{"expireTime":9007200855136812000,"key":"create-remote-file-node-headers-https://instagram.fewr1-6.fna.fbcdn.net/v/t51.2885-15/e35/65721684_728738650893645_3984149295711732765_n.jpg?_nc_ht=instagram.fewr1-6.fna.fbcdn.net&_nc_cat=109&_nc_ohc=A73fbCap-oEAX_eYrgl&_nc_tp=18&oh=9eb783471a8fa3195a19b666bef9ea57&oe=5F8D4994","val":{"last-modified":"Sat, 13 Jul 2019 21:38:49 GMT","x-haystack-needlechecksum":"166185212","x-needle-checksum":"1373328869","content-type":"image/jpeg","x-fb-config-version-olb-prod":"911","timing-allow-origin":"*","access-control-allow-origin":"*","cache-control":"max-age=1209600, no-transform","x-fb-config-version-elb-prod":"911","x-fb-config-version-flb-prod":"560","date":"Fri, 18 Sep 2020 02:23:40 GMT","connection":"close","content-length":"140956"}}